{"id":"gen9ubers-1981533682","p1":"thomasp3864","p2":"45g32","format":"[Gen 9] Ubers","log":"|j|\u2606thomasp3864\n|j|\u260645g32\n|inactive|Battle timer is ON: inactive players will automatically lose when time's up.\n|t:|1698913851\n|gametype|singles\n|j|*Lady Monita \u263d\n|player|p1|thomasp3864|1|\n|player|p2|45g32|karen|\n|teamsize|p1|3\n|teamsize|p2|3\n|gen|9\n|tier|[Gen 9] Ubers\n|rated|Tournament battle\n|rule|Sleep Clause Mod: Limit one foe put to sleep\n|rule|Species Clause: Limit one of each Pok\u00e9mon\n|rule|OHKO Clause: OHKO moves are banned\n|rule|Evasion Items Clause: Evasion items are banned\n|rule|Evasion Moves Clause: Evasion moves are banned\n|rule|Endless Battle Clause: Forcing endless battles is banned\n|rule|HP Percentage Mod: HP is shown in percentages\n|rule|Terastal Clause: You cannot Terastallize\n|clearpoke\n|poke|p1|Gallade, M|\n|poke|p1|Scizor, M|\n|poke|p1|Cloyster, M|\n|poke|p2|Annihilape, M|\n|poke|p2|Zacian-*|\n|poke|p2|Palkia|\n|teampreview|1\n|\n|t:|1698913859\n|start\n|switch|p1a: Gallahad|Gallade, M, shiny|100\/100\n|switch|p2a: Annihilape|Annihilape, M|100\/100\n|turn|1\n|\n|t:|1698913867\n|move|p1a: Gallahad|Psycho Cut|p2a: Annihilape\n|-supereffective|p2a: Annihilape\n|-damage|p2a: Annihilape|0 fnt\n|faint|p2a: Annihilape\n|\n|win|thomasp3864\n|n|\u2606thomasp3864|thomasp3864\n|n|\u260645g32|45g32\n|n|*Lady Monita \u263d|ladymonita\n","uploadtime":1698913868,"views":12,"p1id":"thomasp3864","p2id":"45g32","formatid":"gen9ubers","rating":0,"private":0,"password":""}